sampleReddit/__init__.py
samplereddit-0.1.5.dist-info/METADATA
samplereddit-0.1.5.dist-info/WHEEL
samplereddit-0.1.5.dist-info/licenses/LICENSE
samplereddit-0.1.5.dist-info/RECORD
