Metadata-Version: 2.1
Name: sampleReddit
Version: 0.1.5
Summary: Take snowball samples of Reddit data
Project-URL: Homepage, https://github.com/ReedMerrill/sampleReddit
Project-URL: Issues, https://github.com/ReedMerrill/sampleReddit/issues
Author-email: Reed Merrill <reedjmerrill@gmail.com>
License-File: LICENSE
Keywords: data,praw,reddit,sample,snowball,social media
Classifier: License :: OSI Approved :: BSD License
Classifier: Operating System :: OS Independent
Classifier: Programming Language :: Python :: 3
Requires-Python: >=3.10
Requires-Dist: emojis
Requires-Dist: langdetect
Requires-Dist: pandas
Requires-Dist: praw
